caslib.py
caslib.py-2.3.0.dist-info/DESCRIPTION.rst
caslib.py-2.3.0.dist-info/METADATA
caslib.py-2.3.0.dist-info/RECORD
caslib.py-2.3.0.dist-info/WHEEL
caslib.py-2.3.0.dist-info/metadata.json
caslib.py-2.3.0.dist-info/top_level.txt
