Metadata-Version: 2.0
Name: caslib.py
Version: 2.3.0
Summary: CAS Client library
Home-page: https://github.com/iPlantCollaborativeOpenSource/caslib.py
Author: iPlant Collaborative
Author-email: atmodevs@gmail.com
License: UNKNOWN
Platform: UNKNOWN
Requires-Dist: requests (>=2.2.1)
